google_calendar/__init__.py
google_calendar_interface-0.0.2.dist-info/METADATA
google_calendar_interface-0.0.2.dist-info/WHEEL
google_calendar_interface-0.0.2.dist-info/top_level.txt
google_calendar_interface-0.0.2.dist-info/RECORD
