Metadata-Version: 2.1
Name: google-calendar-interface
Version: 0.0.2
Summary: An easy interface for Google Calendar
Home-page: https://github.com/GrantGMiller/google_calendar_interface
Author: Grant miller
Author-email: grant@grant-miller.com
License: PSF
Project-URL: Source Code, https://github.com/GrantGMiller/google_calendar_interface
Keywords: google calendar interface oauth flask grant miller
Platform: UNKNOWN
Requires-Dist: calendar-base
Requires-Dist: requests
